{
  "places": [
    {
      "id": "p1",
      "name": "大阪梅田スカイビル 空中庭園展望台",
      "type": "poi",
      "area": "梅田",
      "priceYen": 1500,
      "url": "https://www.skybldg.co.jp/overview/",
      "lat": "",
      "lon": ""
    },
    {
      "id": "p2",
      "name": "梅田スカイビル 空中庭園レストラン",
      "type": "poi",
      "area": "梅田",
      "priceYen": 4000,
      "url": "https://www.skybldg.co.jp/restaurant/",
      "lat": "",
      "lon": ""
    },
    {
      "id": "p3",
      "name": "HEP FIVE サンタのスケートリンク",
      "type": "poi",
      "area": "梅田",
      "priceYen": 1000,
      "url": "https://www.hepfive.jp/",
      "lat": "",
      "lon": ""
    },
    {
      "id": "p4",
      "name": "肉バル KITCHEN JIRO 梅田",
      "type": "poi",
      "area": "梅田",
      "priceYen": 4000,
      "url": "https://kitchenjiro.owst.jp/",
      "lat": "",
      "lon": ""
    },
    {
      "id": "p5",
      "name": "梅田スカイビル 空中庭園展望台",
      "type": "poi",
      "area": "梅田",
      "priceYen": 1500,
      "url": "https://www.skybldg.co.jp/observatory/",
      "lat": "",
      "lon": ""
    },
    {
      "id": "p6",
      "name": "イタリアンダイニング・カプリ",
      "type": "poi",
      "area": "梅田",
      "priceYen": 2500,
      "url": "https://www.capri-osaka.com/",
      "lat": "",
      "lon": ""
    },
    {
      "id": "p7",
      "name": "梅田スカイビルの空中庭園レストラン",
      "type": "poi",
      "area": "梅田",
      "priceYen": 3500,
      "url": "https://www.skybldg.co.jp/restaurant/",
      "lat": "",
      "lon": ""
    },
    {
      "id": "p8",
      "name": "梅田スカイビルの空中庭園レストラン 夕食",
      "type": "poi",
      "area": "梅田",
      "priceYen": 4000,
      "url": "https://www.skybldg.co.jp/restaurant/",
      "lat": "",
      "lon": ""
    }
  ],
  "days": [
    {
      "day": 1,
      "date": "2025-09-24",
      "stops": [
        {
          "time": "10:00",
          "placeId": "p1",
          "note": "梅田の空を見渡せる展望台で、景色を楽しむ。",
          "costYen": 1500
        },
        {
          "time": "12:30",
          "placeId": "p2",
          "note": "空中庭園レストランでのランチ。",
          "costYen": 4000
        },
        {
          "time": "15:00",
          "placeId": "p3",
          "note": "HEP FIVEでスケートを楽しむ。",
          "costYen": 1000
        },
        {
          "time": "19:00",
          "placeId": "p4",
          "note": "ディナーに最適なバルでグルメを堪能。",
          "costYen": 4000
        }
      ]
    },
    {
      "day": 2,
      "date": "2025-09-25",
      "stops": [
        {
          "time": "09:30",
          "placeId": "p5",
          "note": "梅田の景色を一望できる展望台で一日をスタート。",
          "costYen": 1500
        },
        {
          "time": "12:00",
          "placeId": "p6",
          "note": "イタリアンランチで一休み。",
          "costYen": 2500
        },
        {
          "time": "15:00",
          "placeId": "p7",
          "note": "カフェで休憩。",
          "costYen": 3500
        },
        {
          "time": "18:30",
          "placeId": "p8",
          "note": "フレンチディナーを堪能。",
          "costYen": 4000
        }
      ]
    }
  ],
  "estimates": {
    "totalCostYen": 22000
  },
  "title": "大阪への2日間の旅"
}
